{
  "title": "📱 Социальные сети: история, факты, тренды. 16 вопросов по 20 секунд",
  "questions": [
    {
      "text": "Какая социальная сеть была запущена в 2004 году Марком Цукербергом и его соседями по комнате?",
      "image": "",
      "options": ["MySpace", "Twitter", "Facebook", "LinkedIn"],
      "correct": 2,
      "comment": "Facebook (изначально TheFacebook) был запущен 4 февраля 2004 года как сеть для студентов Гарварда."
    },
    {
      "text": "Как называется функция Instagram для публикации фото и видео, исчезающих через 24 часа?",
      "image": "",
      "options": ["Лента", "Reels", "Stories", "IGTV"],
      "correct": 2,
      "comment": "Stories появились в Instagram в 2016 году по аналогии со Snapchat."
    },
    {
      "text": "Как называлась первая социальная сеть, позволявшая создавать профили и списки друзей, запущенная в 1997 году?",
      "image": "",
      "options": ["Friendster", "SixDegrees.com", "Hi5", "Orkut"],
      "correct": 1,
      "comment": "SixDegrees.com считается первой современной социальной сетью."
    },
    {
      "text": "Какой фильм 2010 года рассказал историю создания Facebook и получил три премии «Оскар»?",
      "image": "",
      "options": ["Джобс", "Социальная сеть", "Марк", "Гений"],
      "correct": 1,
      "comment": "Фильм «Социальная сеть» Дэвида Финчера посвящён созданию Facebook."
    },
    {
      "text": "Какой актив приобрел Facebook в 2014 году примерно за 19 миллиардов долларов?",
      "image": "",
      "options": ["Telegram", "WhatsApp", "Instagram", "Meta"],
      "correct": 1,
      "comment": "Покупка WhatsApp стала одной из крупнейших сделок в истории IT-индустрии."
    },    
    {
      "text": "Какая платформа первой популяризировала исчезающие через 24 часа публикации?",
      "image": "",
      "options": ["Instagram", "Snapchat", "Facebook", "Twitter"],
      "correct": 1,
      "comment": "Именно Snapchat запустил Stories в 2013 году."
    },
    {
      "text": "Как называются виртуальные награды, которые зрители дарят стримерам на Twitch?",
      "image": "",
      "options": ["Значки", "Кубки", "Монеты", "Биты"],
      "correct": 3,
      "comment": "Bits — внутренняя валюта Twitch для поддержки стримеров."
    },
    {
      "text": "Какой скандал с утечкой данных пользователей Facebook стал широко известен в 2018 году?",
      "image": "",
      "options": ["Cambridge Analytica", "Equifax", "Yahoo Breach", "LinkedIn Hack"],
      "correct": 0,
      "comment": "Cambridge Analytica получила данные миллионов пользователей Facebook без их согласия."
    },
    {
      "text": "Какая социальная сеть первой в мире преодолела отметку в 100 миллионов зарегистрированных пользователей?",
      "image": "",
      "options": ["MySpace", "Facebook", "Friendster", "LinkedIn"],
      "correct": 0,
      "comment": "MySpace первой достигла этой отметки ещё до доминирования Facebook."
    },
    {
      "text": "Какая компания приобрела Instagram в 2012 году за 1 миллиард долларов?",
      "image": "",
      "options": ["Google", "Microsoft", "Facebook", "Twitter"],
      "correct": 2,
      "comment": "Сделка стала одной из самых успешных покупок в истории IT."
    },
    {
      "text": "Какой фактор считается ключевым для алгоритма рекомендаций ленты «Для вас» в TikTok?",
      "image": "",
      "options": ["Количество подписчиков автора", "Время просмотра и взаимодействия", "Возраст аккаунта", "Количество публикаций"],
      "correct": 1,
      "comment": "TikTok в первую очередь анализирует просмотры, досмотры, лайки, комментарии и другие действия пользователя."
    },
    {
      "text": "Что означает аббревиатура «DM» в социальных сетях?",
      "image": "",
      "options": ["Download Master", "Daily Mail", "Digital Marketing", "Direct Message"],
      "correct": 3,
      "comment": "DM — личное сообщение между пользователями."
    },
    {
      "text": "В каком году Facebook официально сменил название компании на Meta?",
      "image": "",
      "options": ["2019", "2020", "2021", "2022"],
      "correct": 2,
      "comment": "Ребрендинг был объявлен Марком Цукербергом в октябре 2021 года."
    },
    {
      "text": "Кто считается создателем системы хештегов (#) в Twitter?",
      "image": "",
      "options": ["Джек Дорси", "Крис Мессина", "Биз Стоун", "Эван Уильямс"],
      "correct": 1,
      "comment": "Крис Мессина предложил использовать символ # для группировки сообщений в 2007 году."
    },
    {
      "text": "Что содержал самый первый опубликованный твит Джека Дорси?",
      "image": "",
      "options": [
        "Hello, Twitter!",
        "First tweet",
        "Welcome to Twitter",
        "just setting up my twttr"
      ],
      "correct": 3,
      "comment": "Первый твит был опубликован 21 марта 2006 года: «just setting up my twttr»."
    },
    {
      "text": "Сделка по какой из этих социальных сетей была самой дорогой на момент её заключения?",
      "image": "",
      "options": [
        "Instagram",
        "LinkedIn",
        "WhatsApp",
        "YouTube"
      ],
      "correct": 1,
      "comment": "Приобретение LinkedIn компанией Microsoft за $26,2 млрд в 2016 году стало крупнейшей из перечисленных сделок."
    }
  ]
}