{
  "title": "🎬 Российское кино 2000–2026: жёсткий экзамен (16 вопросов)",
  "questions": [
    {
      "text": "Какой фильм Алексея Балабанова стал продолжением «Брата» и вышел в 2000 году?",
      "image": "",
      "options": ["Брат 2", "Жмурки", "Груз 200", "Война"],
      "correct": 0,
      "comment": "«Брат 2» (2000) — продолжение культового фильма «Брат»."
    },
    {
      "text": "Какой фильм стал первым крупным российским коммерческим хитом с масштабными визуальными эффектами в 2004 году?",
      "image": "",
      "options": ["9 рота", "Ночной дозор", "Сталинград", "Притяжение"],
      "correct": 1,
      "comment": "«Ночной дозор» (2004) стал первым массовым российским блокбастером с заметным использованием CGI."
    },
    {
      "text": "Какой фильм Фёдора Бондарчука стал одним из самых кассовых российских военных фильмов 2005 года?",
      "image": "",
      "options": ["Сталинград", "Обитаемый остров", "Викинг", "9 рота"],
      "correct": 3,
      "comment": "«9 рота» (2005) — военная драма о войне в Афганистане."
    },
    {
      "text": "Какой фильм Павла Лунгина получил широкое признание и вышел в 2006 году?",
      "image": "",
      "options": ["Дирижёр", "Изгнание", "Остров", "Царь"],
      "correct": 2,
      "comment": "«Остров» (2006) с Петром Мамоновым стал одним из самых обсуждаемых российских фильмов."
    },
    {
      "text": "Какой фильм Андрея Звягинцева получил приз Каннского кинофестиваля в 2014 году?",
      "image": "",
      "options": ["Левиафан", "Елена", "Нелюбовь", "Возвращение"],
      "correct": 0,
      "comment": "«Левиафан» (2014) получил приз за лучший сценарий в Каннах и «Золотой глобус»."
    },
    {
      "text": "Какой фильм стал режиссёрским дебютом Жоры Крыжовникова и вышел в 2014 году?",
      "image": "",
      "options": ["Горько!", "Елки", "Самый лучший день", "Лёд"],
      "correct": 0,
      "comment": "«Горько!» (2014) — дебютный и самый известный фильм Крыжовникова."
    },
    {
      "text": "Кто сыграл главную роль в фильме «Салют-7» (2017) о спасении космической станции?",
      "image": "",
      "options": ["Александр Петров", "Павел Прилучный", "Владимир Вдовиченков", "Данила Козловский"],
      "correct": 2,
      "comment": "Главную роль космонавта сыграл Владимир Вдовиченков."
    },
    {
      "text": "Какой фильм Кантемира Балагова был номинирован на Каннский кинофестиваль в 2019 году?",
      "image": "",
      "options": ["Дылда", "Кислота", "Аритмия", "Довлатов"],
      "correct": 0,
      "comment": "«Дылда» (2019) получила награду за режиссуру в программе «Особый взгляд» Канн."
    },
    {
      "text": "Какой фильм стал самым кассовым российским фильмом 2022 года?",
      "image": "",
      "options": ["Холоп 2", "Чебурашка", "Вызов", "Сердце Пармы"],
      "correct": 1,
      "comment": "«Чебурашка» (2022) стал самым кассовым российским фильмом в истории проката в РФ."
    },
    {
      "text": "Кто исполнил главную роль майора Игоря Грома в фильме 2021 года?",
      "image": "",
      "options": ["Тихон Жизневский", "Сергей Горошко", "Александр Петров", "Павел Прилучный"],
      "correct": 0,
      "comment": "Тихон Жизневский сыграл главного героя в «Майор Гром: Чумной Доктор» (2021)."
    },
    {
      "text": "Какой фильм Клим Шипенко частично снимался на борту МКС?",
      "image": "",
      "options": ["Вызов", "Союз спасения", "Салют-7", "Притяжение"],
      "correct": 0,
      "comment": "«Вызов» (2023) — первый художественный фильм, часть сцен которого снята в космосе."
    },
    {
      "text": "Какой фильм Фёдора Бондарчука посвящён событиям в Сталинграде?",
      "image": "",
      "options": ["Сталинград", "Викинг", "9 рота", "Обитаемый остров"],
      "correct": 0,
      "comment": "«Сталинград» (2013) — военная драма о Сталинградской битве."
    },
    {
      "text": "Какой фильм стал дебютом Николая Хомерики в полнометражном кино?",
      "image": "",
      "options": ["Сказка про темноту", "Рейдер", "Ледокол", "Долгая счастливая жизнь"],
      "correct": 0,
      "comment": "«Сказка про темноту» — один из ранних фильмов Хомерики."
    },
    {
      "text": "Какой фильм считается одним из главных российских криминальных хитов начала 2000-х?",
      "image": "",
      "options": ["Бумер", "Жмурки", "Антикиллер", "Ворошиловский стрелок"],
      "correct": 0,
      "comment": "«Бумер» (2003) стал культовым криминальным фильмом начала 2000-х."
    },
    {
      "text": "Какой фильм Тимура Бекмамбетова стал международным проектом с голливудским прокатом?",
      "image": "",
      "options": ["Особо опасен", "Дневной дозор", "Ёлки", "Ночной дозор"],
      "correct": 0,
      "comment": "«Особо опасен» (2008) — международный проект Бекмамбетова с голливудским прокатом."
    },
    {
      "text": "Какой фильм 2017 года Звягинцева стал одним из самых обсуждаемых драм о семье?",
      "image": "",
      "options": ["Нелюбовь", "Текст", "Сердце Пармы", "Дурак"],
      "correct": 0,
      "comment": "«Нелюбовь» (2017) — один из самых обсуждаемых российских фильмов о распаде семьи."
    }
  ]
}
